repoguard-0.3.0.dev-py3.6-nspkg.pth
repoguard/main.py
repoguard/checks/accessrights.py
repoguard/checks/asciiencoded.py
repoguard/checks/caseinsensitivefilenameclash.py
repoguard/checks/checkout.py
repoguard/checks/checkstyle.py
repoguard/checks/keywords.py
repoguard/checks/log.py
repoguard/checks/mantis.py
repoguard/checks/pylint_.py
repoguard/checks/rejecttabs.py
repoguard/checks/unittests.py
repoguard/checks/xmlvalidator.py
repoguard/core/__init__.py
repoguard/core/checker.py
repoguard/core/config.py
repoguard/core/constants.py
repoguard/core/logger.py
repoguard/core/module.py
repoguard/core/process.py
repoguard/core/protocol.py
repoguard/core/transaction.py
repoguard/core/validator.py
repoguard/handlers/buildbot.py
repoguard/handlers/console.py
repoguard/handlers/file.py
repoguard/handlers/hudson.py
repoguard/handlers/mail.py
repoguard/handlers/mantis.py
repoguard/handlers/viewvc.py
repoguard/modules/mantis.py
repoguard/modules/smtp_client.py
repoguard/tools/base.py
repoguard/tools/checker.py
repoguard/tools/config.py
repoguard/tools/repository.py
usr/local/share/repoguard/cfg/logger.conf
usr/local/share/repoguard/cfg/repoguard.conf
usr/local/share/repoguard/cfg/templates/default.tpl.conf
usr/local/share/repoguard/cfg/templates/python.tpl.conf
repoguard-0.3.0.dev.dist-info/AUTHORS
repoguard-0.3.0.dev.dist-info/LICENSE
repoguard-0.3.0.dev.dist-info/METADATA
repoguard-0.3.0.dev.dist-info/WHEEL
repoguard-0.3.0.dev.dist-info/entry_points.txt
repoguard-0.3.0.dev.dist-info/namespace_packages.txt
repoguard-0.3.0.dev.dist-info/top_level.txt
repoguard-0.3.0.dev.dist-info/RECORD
