Metadata-Version: 2.1
Name: repoguard
Version: 0.3.0.dev
Summary: RepoGuard is a framework for Subversion hook scripts.
Home-page: http://repoguard.tigris.org
Author: Deutsches Zentrum fuer Luft- und Raumfahrt e.V. (DLR)
Author-email: tobias.schlauch@dlr.de
License: Apache License Version 2.0
Platform: Linux
Platform: Unix
Platform: Windows
Classifier: Environment :: Console
Classifier: Intended Audience :: Developers
Classifier: Intended Audience :: System Administrators
Classifier: License :: OSI Approved :: Apache Software License
Classifier: Operating System :: POSIX
Classifier: Programming Language :: Python
Classifier: Topic :: Software Development
Classifier: Topic :: Software Development :: Quality Assurance
Classifier: Topic :: Software Development :: Bug Tracking
Classifier: Topic :: Software Development :: Version Control
